{
	"name": "ftp_imshealth_cepbrick",
	"properties": {
		"activities": [
			{
				"name": "source to raw",
				"type": "Copy",
				"dependsOn": [],
				"policy": {
					"timeout": "0.12:00:00",
					"retry": 0,
					"retryIntervalInSeconds": 30,
					"secureOutput": false,
					"secureInput": false
				},
				"userProperties": [],
				"typeProperties": {
					"source": {
						"type": "DelimitedTextSource",
						"additionalColumns": [
							{
								"name": "metadata_str_pipelineRunId",
								"value": {
									"value": "@pipeline().RunId",
									"type": "Expression"
								}
							},
							{
								"name": "metadata_tms_pipelineRunTime",
								"value": {
									"value": "@utcnow()",
									"type": "Expression"
								}
							},
							{
								"name": "parameter_int_yearMonth",
								"value": {
									"value": "@pipeline().parameters.yearMonth",
									"type": "Expression"
								}
							}
						],
						"storeSettings": {
							"type": "FtpReadSettings",
							"recursive": true,
							"enablePartitionDiscovery": false,
							"useBinaryTransfer": true,
							"disableChunking": false
						},
						"formatSettings": {
							"type": "DelimitedTextReadSettings",
							"compressionProperties": {
								"type": "ZipDeflateReadSettings"
							}
						}
					},
					"sink": {
						"type": "ParquetSink",
						"storeSettings": {
							"type": "AzureBlobFSWriteSettings"
						},
						"formatSettings": {
							"type": "ParquetWriteSettings"
						}
					},
					"enableStaging": false,
					"translator": {
						"type": "TabularTranslator",
						"typeConversion": true,
						"typeConversionSettings": {
							"allowDataTruncation": true,
							"treatBooleanAsNumber": false
						}
					}
				},
				"inputs": [
					{
						"referenceName": "ftp_imshealth_cepbrick",
						"type": "DatasetReference",
						"parameters": {
							"yearMonth": {
								"value": "@pipeline().parameters.yearMonth",
								"type": "Expression"
							}
						}
					}
				],
				"outputs": [
					{
						"referenceName": "datalake_parquet",
						"type": "DatasetReference",
						"parameters": {
							"sourceType": "ftp",
							"sourceName": "imshealth",
							"datasetName": "cepbrick",
							"datalakeContainer": "raw"
						}
					}
				]
			}
		],
		"parameters": {
			"yearMonth": {
				"type": "string"
			}
		},
		"folder": {
			"name": "ftp/imshealth/cepBrick"
		},
		"annotations": []
	}
}